logicalpy/__init__.py
logicalpy/base.py
logicalpy/hilbert.py
logicalpy/normal_forms.py
logicalpy/resolution.py
logicalpy/semantics.py
logicalpy-1.2.1.dist-info/METADATA
logicalpy-1.2.1.dist-info/WHEEL
logicalpy-1.2.1.dist-info/licenses/LICENSE
logicalpy-1.2.1.dist-info/RECORD
