Metadata-Version: 2.4
Name: logicalpy
Version: 1.2.1
Summary: A library providing basic functionalities for manipulating propositional logic
Project-URL: Homepage, https://github.com/Cubix1729/logicalpy
Project-URL: Documentation, https://cubix1729.github.io/logicalpy/
Author: Timothée Monin
License-Expression: MIT
License-File: LICENSE
Keywords: formal logic,logic,propositional logic
Classifier: License :: OSI Approved :: MIT License
Classifier: Programming Language :: Python :: 3
Classifier: Programming Language :: Python :: 3.9
Classifier: Programming Language :: Python :: 3.10
Classifier: Programming Language :: Python :: 3.11
Classifier: Programming Language :: Python :: 3.12
Classifier: Programming Language :: Python :: 3.13
Requires-Python: >=3.9
Requires-Dist: lark>=1.2.2
Requires-Dist: tabulate>=0.9.0
Provides-Extra: dev
Requires-Dist: black>=25.1.0; extra == 'dev'
Requires-Dist: coverage-badge>=1.1.2; extra == 'dev'
Requires-Dist: coverage>=7.8.0; extra == 'dev'
Requires-Dist: mkdocs-material>=9.6.13; extra == 'dev'
Requires-Dist: mkdocs>=1.6.1; extra == 'dev'
